rong.py
setup.py
rongcloud_server_sdk_python.egg-info/PKG-INFO
rongcloud_server_sdk_python.egg-info/SOURCES.txt
rongcloud_server_sdk_python.egg-info/dependency_links.txt
rongcloud_server_sdk_python.egg-info/not-zip-safe
rongcloud_server_sdk_python.egg-info/requires.txt
rongcloud_server_sdk_python.egg-info/top_level.txt