Metadata-Version: 1.0
Name: rongcloud-server-sdk-python
Version: 0.0.2
Summary: Rong Cloud Server SDK in Python.
Home-page: https://github.com/rongcloud/server-sdk-python
Author: Rong Cloud
Author-email: support@rongcloud.cn
License: UNKNOWN
Platform: UNKNOWN
